data/__init__.py
data/cmudict-0.7b.txt
english_to_arabic_transphonator/__init__.py
english_to_arabic_transphonator/transphonator.py
english_to_arabic_transphonator-0.0.0.4.dist-info/LICENSE.md
english_to_arabic_transphonator-0.0.0.4.dist-info/METADATA
english_to_arabic_transphonator-0.0.0.4.dist-info/WHEEL
english_to_arabic_transphonator-0.0.0.4.dist-info/top_level.txt
english_to_arabic_transphonator-0.0.0.4.dist-info/RECORD
