Metadata-Version: 2.1
Name: english_to_arabic_transphonator
Version: 0.0.0.4
Summary: Transphonate English words using Arabic script
Home-page: https://github.com/AMR-KELEG/English-to-arabic-transphonator
Author: Amr Keleg
Author-email: amr_mohamed@live.com
License: GPLv3
Platform: UNKNOWN
License-File: LICENSE.md
